ukupacha/CheckPoint.py
ukupacha/Diagram.py
ukupacha/Graph.py
ukupacha/Utils.py
ukupacha/__init__.py
ukupacha/_version.py
UkuPacha-0.0.9a0.dist-info/LICENSE
UkuPacha-0.0.9a0.dist-info/METADATA
UkuPacha-0.0.9a0.dist-info/WHEEL
UkuPacha-0.0.9a0.dist-info/top_level.txt
UkuPacha-0.0.9a0.dist-info/RECORD
