Metadata-Version: 2.1
Name: UkuPacha
Version: 0.0.9a0
Summary: Package to convert SQL queries given a relational model in dictionaries into JSON data
Home-page: https://github.com/colav/UkuPacha
Author: Colav
Author-email: colav@udea.edu.co
License: BSD
License-File: LICENSE
Requires-Dist: pandas
Requires-Dist: numpy
Requires-Dist: joblib (>=1.1.0)
Requires-Dist: cx-Oracle
Requires-Dist: psutil
Requires-Dist: pymongo (>=3.12.0)
Requires-Dist: tqdm
Requires-Dist: SQLAlchemy
Requires-Dist: blockdiag (==2.0.1)
